xarray_custom/__init__.py
xarray_custom/accessor.py
xarray_custom/bases.py
xarray_custom/dataclasses.py
xarray_custom/docstring.py
xarray_custom/special.py
xarray_custom/typing.py
xarray_custom/utils.py
xarray_custom-0.6.2.dist-info/LICENSE
xarray_custom-0.6.2.dist-info/WHEEL
xarray_custom-0.6.2.dist-info/METADATA
xarray_custom-0.6.2.dist-info/RECORD
